{
  "data": [
    {
      "R": "Bruce Stirling",
      "1": "0H 36M 11S",
      "2": "2H 20M 24S",
      "3": "2H 28M 47S",
      "4": "1H 06M 39S",
      "5": "40M 40S",
      "6": "",
      "7": "",
      "8": "",
      "9": "",
      "10": "",
      "T": "8H 23M 54S"
    },
    {
      "R": "Callum Appleby",
      "1": "0H 48M 27S",
      "2": "1H 28M 10S",
      "3": "2H 11M 27S",
      "4": "0H 57M 17S",
      "5": "39M 30S",
      "6": "",
      "7": "",
      "8": "",
      "9": "",
      "10": "",
      "T": "7H 06M 01S"
    },
    {
      "R": "Callum \u24cb www.theracingcollective.com",
      "1": "0H 41M 09S",
      "2": "1H 50M 14S",
      "3": "2H 26M 31S",
      "4": "0H 57M 48S",
      "5": "33M 16S",
      "6": "",
      "7": "",
      "8": "",
      "9": "",
      "10": "",
      "T": "7H 36M 21S"
    },
    {
      "R": "Chris Pitblado",
      "1": "0H 23M 35S",
      "2": "1H 17M 06S",
      "3": "1H 30M 49S",
      "4": "0H 39M 33S",
      "5": "23M 46S",
      "6": "",
      "7": "",
      "8": "",
      "9": "",
      "10": "",
      "T": "4H 54M 20S"
    },
    {
      "R": "David Holgate",
      "1": "0H 28M 06S",
      "2": "1H 16M 45S",
      "3": "1H 50M 06S",
      "4": "0H 52M 34S",
      "5": "33M 47S",
      "6": "",
      "7": "",
      "8": "",
      "9": "",
      "10": "",
      "T": "5H 49M 08S"
    },
    {
      "R": "David Pearson",
      "1": "0H 48M 19S",
      "2": "2H 20M 24S",
      "3": "2H 11M 23S",
      "4": "0H 57M 16S",
      "5": "39M 33S",
      "6": "",
      "7": "",
      "8": "",
      "9": "",
      "10": "",
      "T": "7H 58M 08S"
    },
    {
      "R": "Derek Queenan",
      "1": "0H 35M 43S",
      "2": "1H 31M 47S",
      "3": "2H 03M 06S",
      "4": "1H 00M 53S",
      "5": "34M 39S",
      "6": "",
      "7": "",
      "8": "",
      "9": "",
      "10": "",
      "T": "6H 48M 01S"
    },
    {
      "R": "Graeme Crichton",
      "1": "0H 52M 50S",
      "2": "2H 20M 24S",
      "3": "2H 26M 49S",
      "4": "1H 26M 08S",
      "5": "41M 36S",
      "6": "",
      "7": "",
      "8": "",
      "9": "",
      "10": "",
      "T": "9H 02M 20S"
    },
    {
      "R": "Jeremy Stevenson",
      "1": "1H 27M 46S",
      "2": "1H 34M 37S",
      "3": "2H 18M 35S",
      "4": "1H 26M 08S",
      "5": "49M 38S",
      "6": "",
      "7": "",
      "8": "",
      "9": "",
      "10": "",
      "T": "8H 55M 27S"
    },
    {
      "R": "Jordan Matthews",
      "1": "1H 06M 26S",
      "2": "1H 35M 42S",
      "3": "2H 11M 21S",
      "4": "0H 57M 16S",
      "5": "39M 47S",
      "6": "",
      "7": "",
      "8": "",
      "9": "",
      "10": "",
      "T": "7H 32M 20S"
    },
    {
      "R": "Mike Henley",
      "1": "1H 27M 46S",
      "2": "2H 20M 24S",
      "3": "2H 33M 09S",
      "4": "1H 26M 08S",
      "5": "49M 38S",
      "6": "",
      "7": "",
      "8": "",
      "9": "",
      "10": "",
      "T": "9H 55M 48S"
    },
    {
      "R": "Natalie Wheatley",
      "1": "1H 27M 46S",
      "2": "2H 20M 24S",
      "3": "2H 13M 44S",
      "4": "0H 59M 38S",
      "5": "49M 38S",
      "6": "",
      "7": "",
      "8": "",
      "9": "",
      "10": "",
      "T": "9H 06M 55S"
    },
    {
      "R": "Neil Wilson",
      "1": "0H 35M 17S",
      "2": "1H 42M 59S",
      "3": "2H 25M 51S",
      "4": "0H 59M 38S",
      "5": "36M 53S",
      "6": "",
      "7": "",
      "8": "",
      "9": "",
      "10": "",
      "T": "7H 26M 23S"
    },
    {
      "R": "Nigel Carrick",
      "1": "0H 38M 59S",
      "2": "1H 46M 29S",
      "3": "2H 25M 47S",
      "4": "1H 03M 41S",
      "5": "41M 38S",
      "6": "",
      "7": "",
      "8": "",
      "9": "",
      "10": "",
      "T": "7H 43M 44S"
    },
    {
      "R": "Seonaidh Charity",
      "1": "0H 30M 23S",
      "2": "1H 18M 08S",
      "3": "1H 57M 18S",
      "4": "0H 44M 21S",
      "5": "27M 19S",
      "6": "",
      "7": "",
      "8": "",
      "9": "",
      "10": "",
      "T": "5H 50M 21S"
    },
    {
      "R": "gee hand",
      "1": "1H 27M 46S",
      "2": "2H 11M 55S",
      "3": "2H 33M 09S",
      "4": "1H 04M 59S",
      "5": "48M 12S",
      "6": "",
      "7": "",
      "8": "",
      "9": "",
      "10": "",
      "T": "9H 23M 48S"
    }
  ]
}