{
  "data": [
    {
      "R": "A Owen \ud83d\udeb4\u200d\u2642\ufe0f",
      "T": "2H 17M 12S",
      "10": "0H 14M 15S",
      "1": "0H 07M 28S",
      "3": "0H 08M 45S",
      "2": "0H 07M 52S",
      "5": "0H 15M 07S",
      "4": "0H 13M 32S",
      "7": "0H 23M 06S",
      "6": "0H 09M 55S",
      "9": "0H 30M 38S",
      "8": "0H 06M 34S"
    },
    {
      "R": "Adam Bird",
      "T": "3H 15M 20S",
      "10": "",
      "1": "0H 09M 07S",
      "3": "0H 21M 17S",
      "2": "0H 08M 52S",
      "5": "",
      "4": "0H 14M 12S",
      "7": "",
      "6": "0H 09M 39S",
      "9": "",
      "8": ""
    },
    {
      "R": "Ben Childs",
      "T": "2H 18M 50S",
      "10": "0H 13M 24S",
      "1": "0H 08M 38S",
      "3": "0H 09M 23S",
      "2": "0H 08M 33S",
      "5": "0H 10M 52S",
      "4": "0H 12M 01S",
      "7": "0H 29M 31S",
      "6": "0H 09M 38S",
      "9": "0H 30M 16S",
      "8": "0H 06M 34S"
    },
    {
      "R": "Cameron Duffield",
      "T": "2H 38M 46S",
      "10": "0H 16M 22S",
      "1": "0H 08M 38S",
      "3": "0H 10M 07S",
      "2": "0H 08M 18S",
      "5": "0H 15M 05S",
      "4": "0H 13M 31S",
      "7": "0H 33M 09S",
      "6": "0H 10M 06S",
      "9": "",
      "8": "0H 07M 44S"
    },
    {
      "R": "Danny Fisher \u24cb (Wildcats Racing Team)",
      "T": "2H 45M 41S",
      "10": "",
      "1": "0H 07M 30S",
      "3": "0H 10M 18S",
      "2": "0H 09M 45S",
      "5": "0H 17M 39S",
      "4": "",
      "7": "",
      "6": "",
      "9": "",
      "8": ""
    },
    {
      "R": "Jack Ferguson",
      "T": "1H 58M 05S",
      "10": "0H 08M 58S",
      "1": "0H 07M 27S",
      "3": "0H 08M 00S",
      "2": "0H 07M 23S",
      "5": "0H 08M 57S",
      "4": "0H 14M 58S",
      "7": "0H 24M 07S",
      "6": "0H 07M 17S",
      "9": "0H 24M 20S",
      "8": "0H 06M 38S"
    },
    {
      "R": "Jack Sumner",
      "T": "3H 28M 43S",
      "10": "",
      "1": "0H 08M 26S",
      "3": "0H 32M 10S",
      "2": "0H 08M 26S",
      "5": "",
      "4": "",
      "7": "",
      "6": "",
      "9": "",
      "8": ""
    },
    {
      "R": "Jade Field",
      "T": "2H 22M 18S",
      "10": "0H 11M 14S",
      "1": "0H 08M 40S",
      "3": "0H 11M 10S",
      "2": "0H 08M 47S",
      "5": "0H 09M 42S",
      "4": "0H 10M 08S",
      "7": "0H 30M 51S",
      "6": "0H 09M 43S",
      "9": "0H 35M 46S",
      "8": "0H 06M 17S"
    },
    {
      "R": "Michael Collins",
      "T": "2H 43M 10S",
      "10": "0H 11M 03S",
      "1": "0H 09M 06S",
      "3": "0H 08M 54S",
      "2": "0H 08M 08S",
      "5": "0H 39M 12S",
      "4": "0H 10M 32S",
      "7": "0H 32M 25S",
      "6": "0H 11M 56S",
      "9": "0H 26M 34S",
      "8": "0H 05M 20S"
    },
    {
      "R": "Nico Bartolomeo",
      "T": "3H 07M 19S",
      "10": "",
      "1": "0H 07M 29S",
      "3": "0H 10M 19S",
      "2": "0H 09M 50S",
      "5": "",
      "4": "0H 15M 32S",
      "7": "",
      "6": "",
      "9": "",
      "8": ""
    },
    {
      "R": "Richard Salden",
      "T": "2H 29M 31S",
      "10": "",
      "1": "0H 07M 23S",
      "3": "0H 09M 47S",
      "2": "0H 09M 41S",
      "5": "0H 16M 38S",
      "4": "0H 11M 39S",
      "7": "0H 26M 17S",
      "6": "0H 09M 38S",
      "9": "",
      "8": "0H 06M 20S"
    },
    {
      "R": "pete lunt",
      "T": "2H 17M 25S",
      "10": "0H 10M 23S",
      "1": "0H 08M 27S",
      "3": "0H 09M 34S",
      "2": "0H 08M 57S",
      "5": "0H 18M 35S",
      "4": "0H 13M 04S",
      "7": "0H 26M 42S",
      "6": "0H 09M 35S",
      "9": "0H 25M 14S",
      "8": "0H 06M 54S"
    }
  ]
}